MPCHelloWorld/__init__.py
MPCHelloWorld/mpchelloworld.py
MPCHelloWorld/test_mpchelloworld.py
MPCHelloWorld-18.3.dist-info/DESCRIPTION.rst
MPCHelloWorld-18.3.dist-info/METADATA
MPCHelloWorld-18.3.dist-info/RECORD
MPCHelloWorld-18.3.dist-info/WHEEL
MPCHelloWorld-18.3.dist-info/metadata.json
MPCHelloWorld-18.3.dist-info/top_level.txt
