Metadata-Version: 2.0
Name: MPCHelloWorld
Version: 18.3
Summary: Simple, bare-bones package tofFacilitate MPC development
Home-page: https://mpaynesedun209@bitbucket.org/mpcdev/mpchelloworld.git
Author: Matt Payne
Author-email: matthewjohnpayne@gmail.com
License: MIT
Platform: UNKNOWN
Classifier: Development Status :: 3 - Alpha
Classifier: License :: OSI Approved :: MIT License
Classifier: Operating System :: OS Independent
Classifier: Programming Language :: Python
Classifier: Intended Audience :: Science/Research
Classifier: Topic :: Scientific/Engineering :: Astronomy
Requires-Python: >=3
